{
    "Path Directory": "C:\\Users\\zah48132\\GSK\\Biopharm Model Predictive Control - Documents\\General\\data\\2025-07-21 B7H4 Model",
    "Asset": "B7H4",
    "Training Data Study": "AR25-050, AR25-051, AR25-068",
    "Operator": "Zach Hatzenbeller",
    "Github Link": "https://github.com/gsk-tech/state-space-model",
    "IDBS Number": "EXXXXX",
    "Modeling Data File Name": "AR25-050_051_068 Model Data",
    "Modeling Data Folder Name": "2025-07-22 B7H4 SAM 1000L Model",
    "A & B Matrices Folder Name": "Matrices",
    "Testing Data Size": 0.2,
    "Number Cross Val Splits": 2,
    "Random Seed": 1,
    "Window Length": 2,
    "Target Plotting Label": "IGG",
    "Training Iterations": 3,
    "BasinHopping Temperature": 1000,
    "Process Time": 15,
    "Scaler": "MinMaxScaler",
    "Instability Weights": {
        "Eigenvalue": 100.0,
        "B-matrix Authority": 100.0,
        "B-matrix Condition": 100.0,
        "Controllability": 10000.0
    },
    "Training Batches": [
        "AR25-050-001",
        "AR25-050-003",
        "AR25-050-005",
        "AR25-050-008",
        "AR25-050-009",
        "AR25-050-011",
        "AR25-050-013",
        "AR25-050-014",
        "AR25-050-018",
        "AR25-050-019",
        "AR25-050-020",
        "AR25-050-023",
        "AR25-050-024",
        "AR25-051-003",
        "AR25-051-005",
        "AR25-051-006",
        "AR25-051-007",
        "AR25-051-009",
        "AR25-051-011",
        "AR25-051-013",
        "AR25-051-014",
        "AR25-051-015",
        "AR25-051-016",
        "AR25-051-017",
        "AR25-051-020",
        "AR25-051-021",
        "AR25-051-022",
        "AR25-051-024"
    ],
    "Testing Batches": [
        "AR25-050-007",
        "AR25-051-002",
        "AR25-051-008",
        "AR25-051-012",
        "AR25-051-018",
        "AR25-051-019",
        "AR25-051-023"
    ],
    "Batches to Discard": [
        "AR25-050-002",
        "AR25-050-004",
        "AR25-050-006",
        "AR25-050-010",
        "AR25-050-012",
        "AR25-050-015",
        "AR25-050-016",
        "AR25-050-017",
        "AR25-050-021",
        "AR25-050-022",
        "AR25-051-001",
        "AR25-051-004",
        "AR25-051-010"
    ],
    "Include Data Columns": [
        "Batch",
        "Day"
    ],
    "Model States": [
        "IGG",
        "VCC",
        "Viability",
        "Glutamate",
        "Ammonium"
    ],
    "Data Smoothing List": [
        "IGG",
        "VCC",
        "Viability",
        "Glutamate",
        "Ammonium"
    ],
    "Model Inputs": [
        "Normalized_Bolus_Feed",
        "Temperature_setpoint",
        "pH_setpoint"
    ],
    "Process Variable Weights": [
        100.0,
        10.0,
        10.0,
        10.0,
        10.0
    ],
    "a_matrix": [
        [
            0.021526042690058485,
            0.11896553204433907,
            0.004872975290533459,
            -0.07817536013493653,
            0.04375161062252334
        ],
        [
            -0.4780284989361435,
            0.10465992212814404,
            -0.02480014610431474,
            0.20873385186365992,
            0.14615224165467902
        ],
        [
            -0.10916424762033876,
            0.11387545862051943,
            0.06475787917460005,
            -0.2695775794781657,
            0.05444965039559845
        ],
        [
            0.39518650722659515,
            0.16705881300457034,
            0.24824599043580314,
            -0.871693063486766,
            0.012795043999399165
        ],
        [
            0.1615625843651595,
            -0.05036499828224945,
            0.08301590405029376,
            0.05016777504829784,
            -0.11129877110573735
        ]
    ],
    "b_matrix": [
        [
            0.04238896766009454,
            -0.0003979588521346721,
            -0.0006801236379757438
        ],
        [
            -0.007190648295243618,
            -0.007216671759054677,
            0.027893313572689794
        ],
        [
            -0.06975182591773876,
            6.393142509475858e-05,
            0.012377076738038255
        ],
        [
            -0.0035532328865088623,
            0.08039054871809961,
            -0.013040303610937923
        ],
        [
            -0.014097785419984714,
            -0.017049645320903205,
            -0.07572714968615105
        ]
    ],
    "af_col": [],
    "af_row": [],
    "bf_row": [],
    "rho": 0.0,
    "scaler": {
        "feature_range": [
            0,
            1
        ],
        "copy": true,
        "clip": false,
        "feature_names_in_": [
            "IGG",
            "VCC",
            "Viability",
            "Glutamate",
            "Ammonium",
            "Normalized_Bolus_Feed",
            "Temperature_setpoint",
            "pH_setpoint"
        ],
        "n_features_in_": 8,
        "n_samples_seen_": 421,
        "scale_": [
            0.0002654366121709376,
            0.059234863271126856,
            0.04576659038901603,
            0.0970873786407767,
            0.0831946755407654,
            15.43508764629299,
            0.3333333333333333,
            1.818181818181816
        ],
        "min_": [
            -0.017090720235172597,
            -0.0204064103969032,
            -3.565217391304349,
            -0.06407766990291262,
            -0.039101497504159734,
            0.0,
            -11.666666666666666,
            -12.909090909090892
        ],
        "data_min_": [
            64.3872,
            0.3445,
            77.9,
            0.66,
            0.47,
            0.0,
            35.0,
            7.1
        ],
        "data_max_": [
            3831.765,
            17.22645,
            99.75,
            10.96,
            12.49,
            0.064787452,
            38.0,
            7.65
        ],
        "data_range_": [
            3767.3777999999998,
            16.88195,
            21.849999999999994,
            10.3,
            12.02,
            0.064787452,
            3.0,
            0.5500000000000007
        ]
    },
    "Iterations": 1143846,
    "Model RMSE": 10.233652457535724,
    "States RMSE": {
        "IGG": 210.5611402734043,
        "VCC": 1.5306681594722216,
        "Viability": 1.2649230474642605,
        "Glutamate": 0.5441804275081054,
        "Ammonium": 0.9926965262393279
    },
    "Last Model Training": "2025/10/30 11:33:30",
    "Hidden State": false,
    "Matrix Stability Penalties": {
        "Eigenvalue": {
            "Value": 0.07317032786504352,
            "Penalty": 0.010708086443067387
        },
        "B-matrix Authority": {
            "Value": 0.1434124681955033,
            "Penalty": 0.7337421996429195
        },
        "B-matrix Condition": {
            "Value": 1.0116282680192301,
            "Penalty": 0.48852338293811115
        },
        "Controllability SVD": {
            "Value": 0.019165489111629002,
            "Penalty": 0.0009507670616634009
        }
    }
}