{
    "Path Directory": "C:\\Users\\zah48132\\GSK\\Biopharm Model Predictive Control - Documents\\General\\data\\2025-10-06 TSLP Platform Fit Model",
    "Asset": "TSLP_PF",
    "Training Data Study": "AR25-064",
    "Operator": "Zach Hatzenbeller",
    "Github Link": "https://github.com/gsk-tech/state-space-model",
    "IDBS Number": "EXXXXX",
    "Modeling Data File Name": "AR25-064 Model Data",
    "Modeling Data Folder Name": "2025-10-06 TSLP Platform Fit Model",
    "A & B Matrices Folder Name": "Matrices",
    "Testing Data Size": 0.2,
    "Number Cross Val Splits": 2,
    "Random Seed": 1,
    "Window Length": 2,
    "Target Plotting Label": "IGG",
    "Training Iterations": 2,
    "BasinHopping Temperature": 100,
    "Process Time": 15,
    "Scaler": "MinMaxScaler",
    "Spline Points": 30,
    "Partitions": {},
    "Current Training Partition": 0,
    "Instability Weights": {
        "Eigenvalue": 100.0,
        "B-matrix Authority": 10.0,
        "B-matrix Condition": 10.0,
        "Controllability": 920.0
    },
    "Training Batches": [
        "AR25-064-001",
        "AR25-064-002",
        "AR25-064-003",
        "AR25-064-005",
        "AR25-064-006",
        "AR25-064-007",
        "AR25-064-008",
        "AR25-064-009",
        "AR25-064-010",
        "AR25-064-011",
        "AR25-064-012",
        "AR25-064-013",
        "AR25-064-016",
        "AR25-064-017",
        "AR25-064-018",
        "AR25-064-020",
        "AR25-064-022",
        "AR25-064-023",
        "AR25-064-024"
    ],
    "Testing Batches": [
        "AR25-064-004",
        "AR25-064-014",
        "AR25-064-015",
        "AR25-064-019",
        "AR25-064-021"
    ],
    "Batches to Discard": [],
    "Include Data Columns": [
        "Batch",
        "Day"
    ],
    "Model States": [
        "IGG",
        "VCC",
        "Viability",
        "Glutamate",
        "Ammonium"
    ],
    "Data Smoothing List": [
        "IGG",
        "VCC",
        "Viability",
        "Glutamate",
        "Ammonium"
    ],
    "Data Column Types": {
        "IGG": "smooth",
        "VCC": "smooth",
        "Viability": "smooth",
        "Glutamate": "smooth",
        "Ammonium": "smooth",
        "Normalized_Bolus_Feed": "bolus",
        "Temperature_setpoint": "zoh",
        "pH_setpoint": "zoh",
        "iVCC": "zoh"
    },
    "Model Inputs": [
        "Normalized_Bolus_Feed",
        "Temperature_setpoint",
        "pH_setpoint",
        "iVCC"
    ],
    "Process Variable Weights": [
        10.0,
        1.0,
        1.0,
        1.0,
        1.0
    ],
    "scaler": {
        "feature_range": [
            0,
            1
        ],
        "copy": true,
        "clip": false,
        "feature_names_in_": [
            "IGG",
            "VCC",
            "Viability",
            "Glutamate",
            "Ammonium",
            "Normalized_Bolus_Feed",
            "Temperature_setpoint",
            "pH_setpoint",
            "iVCC"
        ],
        "n_features_in_": 9,
        "n_samples_seen_": 570,
        "scale_": [
            0.00013485156748538276,
            0.05463389480134123,
            0.05434782608695655,
            0.10030090270812436,
            0.06933785574564592,
            19.399999906879998,
            0.6666666666666666,
            2.5000000000000036,
            0.5135315565141478
        ],
        "min_": [
            -0.0069042900371565664,
            -0.03125605121584732,
            -4.396739130434785,
            -0.09929789368104314,
            -0.036600943397406493,
            0.0,
            -23.333333333333332,
            -17.250000000000025,
            -0.293791403481744
        ],
        "data_min_": [
            51.19918267101313,
            0.5721,
            80.9,
            0.9900000000000002,
            0.5278637910533432,
            0.0,
            35.0,
            6.9,
            0.5721
        ],
        "data_max_": [
            7466.76,
            18.875755700114034,
            99.3,
            10.96,
            14.95,
            0.051546392,
            36.5,
            7.3,
            2.5194
        ],
        "data_range_": [
            7415.5608173289875,
            18.303655700114035,
            18.39999999999999,
            9.97,
            14.422136208946656,
            0.051546392,
            1.5,
            0.39999999999999947,
            1.9473
        ]
    },
    "a_matrix": [
        [
            [
                -0.044376945313110476,
                0.03091478795020343,
                0.0837127179403122,
                -0.08169428435542772,
                0.15842823097290878
            ],
            [
                -0.02369959412867967,
                -0.17226379705098308,
                0.13826121917327738,
                0.21869581428234883,
                -0.07398941482714604
            ],
            [
                -0.2448760683551163,
                0.12673017743461557,
                -0.1544086883311724,
                0.14759194315740073,
                -0.17683543910600144
            ],
            [
                0.05310451147963011,
                -0.01942384321151622,
                0.026085748045433167,
                -0.27557575081128094,
                0.36132570595573443
            ],
            [
                0.300262426061364,
                0.03403794035304826,
                0.06392518295828976,
                -0.16421327500568425,
                -0.2947732715778435
            ]
        ]
    ],
    "b_matrix": [
        [
            [
                0.07402304295152691,
                -0.05984715219210344,
                -0.02789805181763572,
                0.010652024069773431
            ],
            [
                -0.03158784130832153,
                0.011270516618451751,
                0.018080224528943572,
                -0.04394802708116788
            ],
            [
                0.06021179033487285,
                0.0411409589508962,
                0.07425400025558822,
                -0.002146033851037247
            ],
            [
                0.0285044164006698,
                0.08171354578180735,
                -0.04425293118310465,
                0.0212689109337225
            ],
            [
                -0.010929104093987198,
                -0.0047945946797715005,
                0.014525684578311363,
                0.08996628358300597
            ]
        ]
    ],
    "Iterations": [
        39259
    ],
    "Model RMSE": [
        25.424193705468884
    ],
    "States RMSE": [
        {
            "IGG": 307.4055713591556,
            "VCC": 1.9000324530549486,
            "Viability": 1.2694920975535553,
            "Glutamate": 1.310864773655952,
            "Ammonium": 1.442111511633221
        }
    ],
    "Last Model Training": [
        "2026/03/13 12:45:26"
    ],
    "Matrix Stability Penalties": [
        {
            "Eigenvalue": {
                "Value": -0.14957784925582523,
                "Penalty": 0.06791329600536489
            },
            "B-matrix Authority": {
                "Value": 0.20620367228501693,
                "Penalty": 0.6301126098937928
            },
            "B-matrix Condition": {
                "Value": 1.2714363627306988,
                "Penalty": 0.6730764901544807
            },
            "Controllability SVD": {
                "Value": 0.02497295657990701,
                "Penalty": 2.5271165537446153e-05
            }
        }
    ]
}