{
    "Asset": "B7H4",
    "Modeling Data File Name": "AR25-050_051_068 Model Data",
    "A & B Matrices Folder Name": "Matrices",
    "Testing Data Size": 0.2,
    "Number Cross Val Splits": 2,
    "Random Seed": 1,
    "Window Length": 2,
    "Target Plotting Label": "IGG",
    "Training Iterations": 2,
    "BasinHopping Temperature": 100,
    "Process Time": 15,
    "Scaler": "MinMaxScaler",
    "Spline Points": 30,
    "Bolus Decay Tau": 1.0,
    "Partitions": {
        "num_partitions": 3,
        "time_partitions": [
            0.0,
            5.0,
            10.0,
            15.0
        ]
    },
    "Instability Weights": {
        "Eigenvalue": 100.0,
        "B-matrix Authority": 10.0,
        "B-matrix Condition": 10.0,
        "Controllability": 920.0
    },
    "Training Batches": [
        "AR25-050-001",
        "AR25-050-003",
        "AR25-050-005",
        "AR25-050-008",
        "AR25-050-009",
        "AR25-050-011",
        "AR25-050-013",
        "AR25-050-014",
        "AR25-050-018",
        "AR25-050-019",
        "AR25-050-020",
        "AR25-050-023",
        "AR25-050-024",
        "AR25-051-003",
        "AR25-051-005",
        "AR25-051-006",
        "AR25-051-007",
        "AR25-051-009",
        "AR25-051-011",
        "AR25-051-013",
        "AR25-051-014",
        "AR25-051-015",
        "AR25-051-016",
        "AR25-051-017",
        "AR25-051-020",
        "AR25-051-021",
        "AR25-051-022",
        "AR25-051-024"
    ],
    "Testing Batches": [
        "AR25-050-007",
        "AR25-051-002",
        "AR25-051-008",
        "AR25-051-012",
        "AR25-051-018",
        "AR25-051-019",
        "AR25-051-023"
    ],
    "Batches to Discard": [
        "AR25-050-002",
        "AR25-050-004",
        "AR25-050-006",
        "AR25-050-010",
        "AR25-050-012",
        "AR25-050-015",
        "AR25-050-016",
        "AR25-050-017",
        "AR25-050-021",
        "AR25-050-022",
        "AR25-051-001",
        "AR25-051-004",
        "AR25-051-010"
    ],
    "Include Data Columns": [
        "Batch",
        "Day"
    ],
    "Model States": [
        "IGG",
        "VCC",
        "Viability",
        "Glutamate",
        "Ammonium"
    ],
    "Data Column Types": {
        "IGG": "smooth",
        "VCC": "smooth",
        "Viability": "smooth",
        "Glutamate": "smooth",
        "Ammonium": "smooth",
        "Normalized_Bolus_Feed": "bolus",
        "Temperature_setpoint": "zoh",
        "pH_setpoint": "zoh"
    },
    "Model Inputs": [
        "Normalized_Bolus_Feed",
        "Temperature_setpoint",
        "pH_setpoint"
    ],
    "Process Variable Weights": [
        30.0,
        3.5,
        3.5,
        3.5,
        3.5
    ],
    "scaler": {
        "feature_range": [
            0,
            1
        ],
        "copy": true,
        "clip": false,
        "feature_names_in_": [
            "IGG",
            "VCC",
            "Viability",
            "Glutamate",
            "Ammonium",
            "Normalized_Bolus_Feed",
            "Temperature_setpoint",
            "pH_setpoint"
        ],
        "n_features_in_": 8,
        "n_samples_seen_": 840,
        "scale_": [
            0.00026495309745320974,
            0.059658256950600765,
            0.04564810724413104,
            0.0970873786407767,
            0.08319467554076539,
            17.663531760741247,
            0.3333333333333333,
            1.818181818181816
        ],
        "min_": [
            -0.015238005462798243,
            -0.020552269519481962,
            -3.5559875543178086,
            -0.06407766990291262,
            -0.03910149750415973,
            0.0,
            -11.666666666666666,
            -12.909090909090892
        ],
        "data_min_": [
            57.51208651368663,
            0.3445,
            77.9,
            0.66,
            0.47,
            0.0,
            35.0,
            7.1
        ],
        "data_max_": [
            3831.765,
            17.106639075367838,
            99.80671334195505,
            10.96,
            12.490000000000002,
            0.05661381956594818,
            38.0,
            7.65
        ],
        "data_range_": [
            3774.2529134863134,
            16.762139075367838,
            21.90671334195504,
            10.3,
            12.020000000000001,
            0.05661381956594818,
            3.0,
            0.5500000000000007
        ]
    },
    "a_matrix": [
        [
            [
                -0.6457499639635146,
                -0.11189999424378336,
                -0.05283680302181776,
                0.22029226345272335,
                0.13554589891681829
            ],
            [
                -0.09795196289923926,
                -0.40683762421194114,
                -0.10828868080512205,
                0.36038513674604833,
                0.30926208658590326
            ],
            [
                -0.0417262444057869,
                0.30968074215846,
                -0.021558751727373024,
                0.02172769470880034,
                0.05925139709615529
            ],
            [
                -0.10109838958253445,
                -0.20348852428598505,
                0.09762676037012798,
                -0.3736838945853495,
                0.18614361099547916
            ],
            [
                0.3250768747270483,
                0.06432137500567617,
                0.1812914434526728,
                -0.2150590610547279,
                -0.2427939291570518
            ]
        ],
        [
            [
                -0.4228176452540361,
                0.1674420418142243,
                0.11686335838111299,
                -0.4135408209469941,
                0.4157859294840307
            ],
            [
                0.17502457554568782,
                -0.5731058396959555,
                0.03999346841025339,
                0.1597498512221111,
                0.4973547358867382
            ],
            [
                -0.40799003967632025,
                0.17239364439742003,
                -0.2234569436054733,
                0.3917921157266156,
                -0.19457396093143342
            ],
            [
                0.43882769118198106,
                -0.0653075655869064,
                -0.10833406981405704,
                -0.13636970034971282,
                0.4611085229251475
            ],
            [
                0.07325869796217808,
                -0.19891870584251586,
                0.45911158931589635,
                -0.3683661092538291,
                -0.3789538097479965
            ]
        ],
        [
            [
                -0.32365354703226334,
                0.2455058209015455,
                -0.08089834476154936,
                0.04875968034986957,
                0.08605602446587597
            ],
            [
                -0.019882725731627256,
                0.04121487404048639,
                0.24511989798911207,
                -0.3806538335476151,
                0.055265362317464956
            ],
            [
                -0.04610993574557646,
                -0.1778581512061198,
                -0.15956823846271104,
                0.10097241756663827,
                0.3345704722567977
            ],
            [
                -0.22891171680138142,
                0.5898815851855388,
                -0.20030510788857975,
                -0.34580376989591965,
                0.18771209424944416
            ],
            [
                0.05741751948013117,
                0.4178612173539843,
                -0.1471905085085445,
                -0.006629404235024675,
                -0.28910838799255717
            ]
        ]
    ],
    "b_matrix": [
        [
            [
                0.13528771503656337,
                -0.017452845310517127,
                0.04482456518490642
            ],
            [
                0.1070275121046748,
                0.07566624496046241,
                0.11617815669685908
            ],
            [
                -0.04260810763694727,
                -0.05194331359731201,
                -0.004531571773447658
            ],
            [
                0.09810904889487806,
                0.1665566109581994,
                -0.06089175973925618
            ],
            [
                0.17118111425198337,
                -0.046420846127018946,
                -0.0820128037227328
            ]
        ],
        [
            [
                0.15973836390716895,
                -0.03898933768893408,
                0.053514263481629035
            ],
            [
                0.1286392574590921,
                0.07957322880181947,
                0.18869081051238423
            ],
            [
                0.243237135863103,
                -0.0808712522058531,
                -0.0648987493793981
            ],
            [
                -0.194309739365834,
                -0.031914893163578144,
                0.14035194499773718
            ],
            [
                -0.009637800515524878,
                0.23153041199451455,
                -0.09900986129942563
            ]
        ],
        [
            [
                0.18940217784554603,
                -0.06918204739426301,
                0.03804885235414
            ],
            [
                0.18526170208652745,
                0.009818332029201807,
                0.0069989047163386674
            ],
            [
                -0.09125903129744826,
                -0.2534542124629933,
                0.23963559166140394
            ],
            [
                -0.06088827408321859,
                -0.0694116483326069,
                0.14157467425547327
            ],
            [
                0.011611688092186814,
                -0.06652580409928918,
                -0.2791645988206042
            ]
        ]
    ],
    "Iterations": 114602,
    "Model RMSE": 37.014265827581404,
    "States RMSE": {
        "IGG": 261.4724713498925,
        "VCC": 1.9274181393337106,
        "Viability": 1.9796207980429963,
        "Glutamate": 0.8102686493498427,
        "Ammonium": 1.2995402673753078
    },
    "Last Model Training": "2026/04/15 10:08:37",
    "Matrix Stability Penalties": {
        "Eigenvalue": {
            "Value": 0.03018696480434664,
            "Penalty": 0.3592178801786289
        },
        "B-matrix Authority": {
            "Value": 0.48684616732669855,
            "Penalty": 0.8119149913063031
        },
        "B-matrix Condition": {
            "Value": 1.7564952111210141,
            "Penalty": 3.0842145741783407
        },
        "Controllability SVD": {
            "Value": 0.043858250633848336,
            "Penalty": 1.793891933209385e-06
        }
    }
}